scenario_testing_tools/__init__.py
scenario_testing_tools/generate_refline.py
scenario_testing_tools/get_scene_ego_traj.py
scenario_testing_tools/get_scene_timesample.py
scenario_testing_tools/get_scene_track.py
scenario_testing_tools/get_scene_veh_param.py
scenario_testing_tools/interp_heading.py
scenario_testing_tools-0.82.dist-info/LICENSE
scenario_testing_tools-0.82.dist-info/METADATA
scenario_testing_tools-0.82.dist-info/WHEEL
scenario_testing_tools-0.82.dist-info/top_level.txt
scenario_testing_tools-0.82.dist-info/RECORD
