Metadata-Version: 2.1
Name: scenario-testing-tools
Version: 0.82
Summary: Useful functions used together with a (currently private) scenario generation tool.
Home-page: UNKNOWN
Author: Tim Stahl
Author-email: stahl@ftm.mw.tum.de
License: UNKNOWN
Platform: UNKNOWN
Classifier: Programming Language :: Python :: 3
Classifier: Programming Language :: Python :: 3.5
Classifier: Programming Language :: Python :: 3.6
Classifier: Programming Language :: Python :: 3.7
Classifier: License :: OSI Approved :: GNU Lesser General Public License v3 (LGPLv3)
Classifier: Operating System :: OS Independent
Requires-Dist: pandas (==0.25.3)
Requires-Dist: Shapely (==1.7.0)
